{"createdDate":"2025-09-14T04:44:52Z","version":"1.0","experimentIDs":["1DC09FCA-DCC8-4CEC-AE32-E902C8450C2D"],"id":"D8E54DCA-1C53-4138-B0FA-548F6C4E4888","activityEntities":["dataSourceTrainingStarted",[{"event":"dataSourceTrainingStarted","title":"Used By","id":"50CDADDB-4B3C-468D-A19F-4BCC8754D80E","createdDate":"2025-09-14T04:45:51Z","subtitle":"ImageClassifier 1"}],"dataSourceMetrics",[{"event":"dataSourceMetrics","id":"C6456A2E-3345-4CD8-93CA-32C9F967ECF9","subtitle":"2 Classes, 24 Items","createdDate":"2025-09-14T04:45:51Z","title":"Data Summary"}],"dataSourceCreated",[{"title":"Data Source Created","createdDate":"2025-09-14T04:44:52Z","event":"dataSourceCreated","subtitle":"训练数据","id":"30F4E734-6B11-481A-8AD4-FD60CEE07BF3"}]],"pathType":0,"title":"训练数据","modifiedDate":"2025-09-14T04:45:51Z","dataResult":{"classesCount":2,"itemsCount":24,"createdDate":"2025-09-14T04:44:52Z","dataSourceID":"D8E54DCA-1C53-4138-B0FA-548F6C4E4888","dataAnalysis":{"summary":{"classCount":2,"canUseValidation":0,"sampleCount":24},"issues":[{"severity":"debug","description":"2 classes found, including Dog, Cat"},{"severity":"warning","description":"Less than 50 total images found - add more to improve model validation"},{"description":"Smallest class is \"Cat\" with 12 images","severity":"debug"},{"severity":"debug","description":"Largest class is \"Dog\" with 12 images"}],"classifierAnalysis":{"details":["file:\/\/\/Users\/huipukui\/Desktop\/AllFile\/IOS_UIKIT\/IOS_UIKIT\/%E8%BF%9B%E9%98%B6%E7%89%88-18-AI%E6%9C%BA%E5%99%A8%E5%AD%A6%E4%B9%A0-CoreML2\/Image\/%E8%AE%AD%E7%BB%83%E6%95%B0%E6%8D%AE\/Cat\/Unknown-5.jpeg",["Cat"],"file:\/\/\/Users\/huipukui\/Desktop\/AllFile\/IOS_UIKIT\/IOS_UIKIT\/%E8%BF%9B%E9%98%B6%E7%89%88-18-AI%E6%9C%BA%E5%99%A8%E5%AD%A6%E4%B9%A0-CoreML2\/Image\/%E8%AE%AD%E7%BB%83%E6%95%B0%E6%8D%AE\/Dog\/images-4.jpeg",["Dog"],"file:\/\/\/Users\/huipukui\/Desktop\/AllFile\/IOS_UIKIT\/IOS_UIKIT\/%E8%BF%9B%E9%98%B6%E7%89%88-18-AI%E6%9C%BA%E5%99%A8%E5%AD%A6%E4%B9%A0-CoreML2\/Image\/%E8%AE%AD%E7%BB%83%E6%95%B0%E6%8D%AE\/Dog\/Unknown-1.jpeg",["Dog"],"file:\/\/\/Users\/huipukui\/Desktop\/AllFile\/IOS_UIKIT\/IOS_UIKIT\/%E8%BF%9B%E9%98%B6%E7%89%88-18-AI%E6%9C%BA%E5%99%A8%E5%AD%A6%E4%B9%A0-CoreML2\/Image\/%E8%AE%AD%E7%BB%83%E6%95%B0%E6%8D%AE\/Dog\/Unknown.jpeg",["Dog"],"file:\/\/\/Users\/huipukui\/Desktop\/AllFile\/IOS_UIKIT\/IOS_UIKIT\/%E8%BF%9B%E9%98%B6%E7%89%88-18-AI%E6%9C%BA%E5%99%A8%E5%AD%A6%E4%B9%A0-CoreML2\/Image\/%E8%AE%AD%E7%BB%83%E6%95%B0%E6%8D%AE\/Dog\/Unknown-6.jpeg",["Dog"],"file:\/\/\/Users\/huipukui\/Desktop\/AllFile\/IOS_UIKIT\/IOS_UIKIT\/%E8%BF%9B%E9%98%B6%E7%89%88-18-AI%E6%9C%BA%E5%99%A8%E5%AD%A6%E4%B9%A0-CoreML2\/Image\/%E8%AE%AD%E7%BB%83%E6%95%B0%E6%8D%AE\/Dog\/images.jpeg",["Dog"],"file:\/\/\/Users\/huipukui\/Desktop\/AllFile\/IOS_UIKIT\/IOS_UIKIT\/%E8%BF%9B%E9%98%B6%E7%89%88-18-AI%E6%9C%BA%E5%99%A8%E5%AD%A6%E4%B9%A0-CoreML2\/Image\/%E8%AE%AD%E7%BB%83%E6%95%B0%E6%8D%AE\/Dog\/Unknown-2.jpeg",["Dog"],"file:\/\/\/Users\/huipukui\/Desktop\/AllFile\/IOS_UIKIT\/IOS_UIKIT\/%E8%BF%9B%E9%98%B6%E7%89%88-18-AI%E6%9C%BA%E5%99%A8%E5%AD%A6%E4%B9%A0-CoreML2\/Image\/%E8%AE%AD%E7%BB%83%E6%95%B0%E6%8D%AE\/Cat\/Unknown-7.jpeg",["Cat"],"file:\/\/\/Users\/huipukui\/Desktop\/AllFile\/IOS_UIKIT\/IOS_UIKIT\/%E8%BF%9B%E9%98%B6%E7%89%88-18-AI%E6%9C%BA%E5%99%A8%E5%AD%A6%E4%B9%A0-CoreML2\/Image\/%E8%AE%AD%E7%BB%83%E6%95%B0%E6%8D%AE\/Cat\/Unknown-2.jpeg",["Cat"],"file:\/\/\/Users\/huipukui\/Desktop\/AllFile\/IOS_UIKIT\/IOS_UIKIT\/%E8%BF%9B%E9%98%B6%E7%89%88-18-AI%E6%9C%BA%E5%99%A8%E5%AD%A6%E4%B9%A0-CoreML2\/Image\/%E8%AE%AD%E7%BB%83%E6%95%B0%E6%8D%AE\/Dog\/images-2.jpeg",["Dog"],"file:\/\/\/Users\/huipukui\/Desktop\/AllFile\/IOS_UIKIT\/IOS_UIKIT\/%E8%BF%9B%E9%98%B6%E7%89%88-18-AI%E6%9C%BA%E5%99%A8%E5%AD%A6%E4%B9%A0-CoreML2\/Image\/%E8%AE%AD%E7%BB%83%E6%95%B0%E6%8D%AE\/Cat\/Unknown-1.jpeg",["Cat"],"file:\/\/\/Users\/huipukui\/Desktop\/AllFile\/IOS_UIKIT\/IOS_UIKIT\/%E8%BF%9B%E9%98%B6%E7%89%88-18-AI%E6%9C%BA%E5%99%A8%E5%AD%A6%E4%B9%A0-CoreML2\/Image\/%E8%AE%AD%E7%BB%83%E6%95%B0%E6%8D%AE\/Cat\/Unknown-8.jpeg",["Cat"],"file:\/\/\/Users\/huipukui\/Desktop\/AllFile\/IOS_UIKIT\/IOS_UIKIT\/%E8%BF%9B%E9%98%B6%E7%89%88-18-AI%E6%9C%BA%E5%99%A8%E5%AD%A6%E4%B9%A0-CoreML2\/Image\/%E8%AE%AD%E7%BB%83%E6%95%B0%E6%8D%AE\/Cat\/Unknown-4.jpeg",["Cat"],"file:\/\/\/Users\/huipukui\/Desktop\/AllFile\/IOS_UIKIT\/IOS_UIKIT\/%E8%BF%9B%E9%98%B6%E7%89%88-18-AI%E6%9C%BA%E5%99%A8%E5%AD%A6%E4%B9%A0-CoreML2\/Image\/%E8%AE%AD%E7%BB%83%E6%95%B0%E6%8D%AE\/Cat\/Unknown-10.jpeg",["Cat"],"file:\/\/\/Users\/huipukui\/Desktop\/AllFile\/IOS_UIKIT\/IOS_UIKIT\/%E8%BF%9B%E9%98%B6%E7%89%88-18-AI%E6%9C%BA%E5%99%A8%E5%AD%A6%E4%B9%A0-CoreML2\/Image\/%E8%AE%AD%E7%BB%83%E6%95%B0%E6%8D%AE\/Cat\/Unknown-3.jpeg",["Cat"],"file:\/\/\/Users\/huipukui\/Desktop\/AllFile\/IOS_UIKIT\/IOS_UIKIT\/%E8%BF%9B%E9%98%B6%E7%89%88-18-AI%E6%9C%BA%E5%99%A8%E5%AD%A6%E4%B9%A0-CoreML2\/Image\/%E8%AE%AD%E7%BB%83%E6%95%B0%E6%8D%AE\/Cat\/Unknown-6.jpeg",["Cat"],"file:\/\/\/Users\/huipukui\/Desktop\/AllFile\/IOS_UIKIT\/IOS_UIKIT\/%E8%BF%9B%E9%98%B6%E7%89%88-18-AI%E6%9C%BA%E5%99%A8%E5%AD%A6%E4%B9%A0-CoreML2\/Image\/%E8%AE%AD%E7%BB%83%E6%95%B0%E6%8D%AE\/Cat\/Unknown.jpeg",["Cat"],"file:\/\/\/Users\/huipukui\/Desktop\/AllFile\/IOS_UIKIT\/IOS_UIKIT\/%E8%BF%9B%E9%98%B6%E7%89%88-18-AI%E6%9C%BA%E5%99%A8%E5%AD%A6%E4%B9%A0-CoreML2\/Image\/%E8%AE%AD%E7%BB%83%E6%95%B0%E6%8D%AE\/Cat\/Unknown-9.jpeg",["Cat"],"file:\/\/\/Users\/huipukui\/Desktop\/AllFile\/IOS_UIKIT\/IOS_UIKIT\/%E8%BF%9B%E9%98%B6%E7%89%88-18-AI%E6%9C%BA%E5%99%A8%E5%AD%A6%E4%B9%A0-CoreML2\/Image\/%E8%AE%AD%E7%BB%83%E6%95%B0%E6%8D%AE\/Dog\/images-3.jpeg",["Dog"],"file:\/\/\/Users\/huipukui\/Desktop\/AllFile\/IOS_UIKIT\/IOS_UIKIT\/%E8%BF%9B%E9%98%B6%E7%89%88-18-AI%E6%9C%BA%E5%99%A8%E5%AD%A6%E4%B9%A0-CoreML2\/Image\/%E8%AE%AD%E7%BB%83%E6%95%B0%E6%8D%AE\/Cat\/Unknown-11.jpeg",["Cat"],"file:\/\/\/Users\/huipukui\/Desktop\/AllFile\/IOS_UIKIT\/IOS_UIKIT\/%E8%BF%9B%E9%98%B6%E7%89%88-18-AI%E6%9C%BA%E5%99%A8%E5%AD%A6%E4%B9%A0-CoreML2\/Image\/%E8%AE%AD%E7%BB%83%E6%95%B0%E6%8D%AE\/Dog\/Unknown-3.jpeg",["Dog"],"file:\/\/\/Users\/huipukui\/Desktop\/AllFile\/IOS_UIKIT\/IOS_UIKIT\/%E8%BF%9B%E9%98%B6%E7%89%88-18-AI%E6%9C%BA%E5%99%A8%E5%AD%A6%E4%B9%A0-CoreML2\/Image\/%E8%AE%AD%E7%BB%83%E6%95%B0%E6%8D%AE\/Dog\/Unknown-5.jpeg",["Dog"],"file:\/\/\/Users\/huipukui\/Desktop\/AllFile\/IOS_UIKIT\/IOS_UIKIT\/%E8%BF%9B%E9%98%B6%E7%89%88-18-AI%E6%9C%BA%E5%99%A8%E5%AD%A6%E4%B9%A0-CoreML2\/Image\/%E8%AE%AD%E7%BB%83%E6%95%B0%E6%8D%AE\/Dog\/Unknown-4.jpeg",["Dog"],"file:\/\/\/Users\/huipukui\/Desktop\/AllFile\/IOS_UIKIT\/IOS_UIKIT\/%E8%BF%9B%E9%98%B6%E7%89%88-18-AI%E6%9C%BA%E5%99%A8%E5%AD%A6%E4%B9%A0-CoreML2\/Image\/%E8%AE%AD%E7%BB%83%E6%95%B0%E6%8D%AE\/Dog\/images-1.jpeg",["Dog"]],"labelStats":{"Cat":12,"Dog":12}},"objectDetectorAnalysis":{"details":{}}},"dataURL":"file:\/\/\/Users\/huipukui\/Desktop\/AllFile\/IOS_UIKIT\/IOS_UIKIT\/%E8%BF%9B%E9%98%B6%E7%89%88-18-AI%E6%9C%BA%E5%99%A8%E5%AD%A6%E4%B9%A0-CoreML2\/Image\/%E8%AE%AD%E7%BB%83%E6%95%B0%E6%8D%AE\/"},"preferredFilename":"训练数据","dataURL":"file:\/\/\/Users\/huipukui\/Desktop\/AllFile\/IOS_UIKIT\/IOS_UIKIT\/%E8%BF%9B%E9%98%B6%E7%89%88-18-AI%E6%9C%BA%E5%99%A8%E5%AD%A6%E4%B9%A0-CoreML2\/Image\/%E8%AE%AD%E7%BB%83%E6%95%B0%E6%8D%AE\/","dataPathRelativeToProjectURL":"..\/%E8%AE%AD%E7%BB%83%E6%95%B0%E6%8D%AE\/"}